README.rst
setup.py
deepauth/__init__.py
deepauth/models.py
deepauth/serializers.py
deepauth/urls.py
deepauth/views.py
deepauth.egg-info/PKG-INFO
deepauth.egg-info/SOURCES.txt
deepauth.egg-info/dependency_links.txt
deepauth.egg-info/requires.txt
deepauth.egg-info/top_level.txt
deepauth/utils/__init__.py
deepauth/utils/captcha.py
deepauth/utils/mailbox.py
deepauth/utils/password.py
deepauth/utils/token.py