Metadata-Version: 2.1
Name: deepauth
Version: 2.4.17
Summary: Deepera Authentication System
Home-page: https://github.com/valency/deepauth/
Author: Deepera Co., Ltd.
Author-email: yding@deepera.com
License: UNKNOWN
Keywords: tokenetf,tokenmds,mds
Platform: UNKNOWN
